LICENSE
anime_dl/__init__.py
anime_dl/main.py
anime_dl/scraper/__init__.py
anime_dl-0.1.1.dist-info/entry_points.txt
anime_dl-0.1.1.dist-info/LICENSE
anime_dl-0.1.1.dist-info/WHEEL
anime_dl-0.1.1.dist-info/METADATA
anime_dl-0.1.1.dist-info/RECORD
